Metadata-Version: 2.1
Name: a-pandas-ex-whatsapp-to-df
Version: 0.10
Summary: Use the power of pandas to search through your WhatsApp messages (Doesn't require root access!)
Home-page: https://github.com/hansalemaos/a_pandas_ex_whatsapp_to_df
Author: Johannes Fischer
Author-email: <aulasparticularesdealemaosp@gmail.com>
License: MIT
Keywords: pandas,DataFrame,WhatsApp,messages
Classifier: Development Status :: 4 - Beta
Classifier: Programming Language :: Python :: 3 :: Only
Classifier: Programming Language :: Python :: 3.9
Classifier: Topic :: Scientific/Engineering :: Visualization
Classifier: Topic :: Software Development :: Libraries :: Python Modules
Classifier: Topic :: Text Editors :: Text Processing
Classifier: Topic :: Text Processing :: General
Classifier: Topic :: Text Processing :: Indexing
Classifier: Topic :: Text Processing :: Filters
Classifier: Topic :: Utilities
License-File: LICENSE.rst
Requires-Dist: a-pandas-ex-read-sql
Requires-Dist: pandas
Requires-Dist: touchtouch
